README.md
setup.cfg
setup.py
credulous/__init__.py
credulous/__main__.py
credulous/credulous.py
credulous.egg-info/PKG-INFO
credulous.egg-info/SOURCES.txt
credulous.egg-info/dependency_links.txt
credulous.egg-info/entry_points.txt
credulous.egg-info/requires.txt
credulous.egg-info/top_level.txt