Metadata-Version: 1.0
Name: credulous
Version: 0.3.1
Summary: Tool for generating API credentials
Home-page: https://github.com/davido-brainlabs/pycredulous
Author: David O'Connor
Author-email: david.o@brainlabsdigital.com
License: UNKNOWN
Platform: UNKNOWN
